README.rst
setup.py
cache_magic/__init__.py
ipython_cache.egg-info/PKG-INFO
ipython_cache.egg-info/SOURCES.txt
ipython_cache.egg-info/dependency_links.txt
ipython_cache.egg-info/requires.txt
ipython_cache.egg-info/top_level.txt